README.rst
setup.py
ETLT_pgSQL.egg-info/PKG-INFO
ETLT_pgSQL.egg-info/SOURCES.txt
ETLT_pgSQL.egg-info/dependency_links.txt
ETLT_pgSQL.egg-info/requires.txt
ETLT_pgSQL.egg-info/top_level.txt
etlt_pgsql/__init__.py
etlt_pgsql/writer/PgSqlLoaderWriter.py
etlt_pgsql/writer/__init__.py
test/writer/PgSqlLoaderWriterTest.py
test/writer/__init__.py