Metadata-Version: 1.1
Name: ETLT-pgSQL
Version: 0.10.0
Summary: ETLT extension for MariaDB and MySQL databases
Home-page: https://github.com/SetBased/py-etlt-mysql
Author: Paul Water
Author-email: info@setbased.nl
License: MIT
Keywords: ETLT,PostgreSQL
Platform: UNKNOWN
Classifier: Development Status :: 3 - Alpha
Classifier: Environment :: Console
Classifier: Intended Audience :: Developers
Classifier: License :: OSI Approved :: MIT License
Classifier: Operating System :: OS Independent
Classifier: Programming Language :: Python :: 3
Classifier: Programming Language :: Python :: 3.4
Classifier: Programming Language :: Python :: 3.5
Classifier: Programming Language :: Python :: 3.6
Classifier: Topic :: Database
